xontrib/add_variable/__init__.py
xontrib/add_variable/decorators.xsh
xontrib_add_variable-1.2.0.dist-info/LICENSE
xontrib_add_variable-1.2.0.dist-info/METADATA
xontrib_add_variable-1.2.0.dist-info/WHEEL
xontrib_add_variable-1.2.0.dist-info/top_level.txt
xontrib_add_variable-1.2.0.dist-info/RECORD
