Metadata-Version: 2.1
Name: xontrib-add-variable
Version: 1.2.0
Summary: This package allow add new variable.
Home-page: https://github.com/ErickTucto/xontrib-add-variable
Author: Erick Tucto
Author-email: erick.tucto@outlook.com
License: MIT
Platform: any
